packelf/__init__.py
packelf/cli.py
packelf-0.2.0.dist-info/entry_points.txt
packelf-0.2.0.dist-info/LICENSE
packelf-0.2.0.dist-info/WHEEL
packelf-0.2.0.dist-info/METADATA
packelf-0.2.0.dist-info/RECORD
